<?xml version = '1.0' encoding = 'UTF-8'?>
<TableProxyOraclev20c class="oracle.dbtools.crest.model.design.storage.oracle.v20c.TableProxyOraclev20c" name="usuario" directorySegmentName="seg_0" id="B899A6D9-CB61-AB05-A717-F5AB7C6DA89C">
<createdBy>usuario</createdBy>
<createdTime>2026-03-19 19:55:15 UTC</createdTime>
<ownerDesignName>DMD</ownerDesignName>
<logging>YES</logging>
<partitionedRowMovement>DISABLE</partitionedRowMovement>
<temporaryChanged>false</temporaryChanged>
<accessDriverType>oracle_loader</accessDriverType>
<rejectLimit></rejectLimit>
<columnProxies itemClass="oracle.dbtools.crest.model.design.storage.oracle.v12c.ColumnProxyOraclev12c">
<ColumnProxy name="fecha_nac" id="846F7A7C-C7B0-3BE1-02AC-9CCCE8A7ABF0">
<createdBy>usuario</createdBy>
<createdTime>2026-03-19 19:55:15 UTC</createdTime>
<ownerDesignName>DMD</ownerDesignName>
</ColumnProxy>
<ColumnProxy name="apellido1" id="90EBC1F7-58BD-A10C-24A5-4388B9CC1916">
<createdBy>usuario</createdBy>
<createdTime>2026-03-19 19:55:15 UTC</createdTime>
<ownerDesignName>DMD</ownerDesignName>
</ColumnProxy>
<ColumnProxy name="id_centro" id="A8ED8616-067D-0B29-8E89-77A1BC4887D7">
<createdBy>usuario</createdBy>
<createdTime>2026-03-19 19:55:15 UTC</createdTime>
<ownerDesignName>DMD</ownerDesignName>
</ColumnProxy>
<ColumnProxy name="apellido2" id="AE847E67-EE6C-6F09-BD02-2EDE85F381EC">
<createdBy>usuario</createdBy>
<createdTime>2026-03-19 19:55:15 UTC</createdTime>
<ownerDesignName>DMD</ownerDesignName>
</ColumnProxy>
<ColumnProxy name="dni" id="DA6ED907-9D53-0C92-28D2-B6470C671B58">
<createdBy>usuario</createdBy>
<createdTime>2026-03-19 19:55:15 UTC</createdTime>
<ownerDesignName>DMD</ownerDesignName>
</ColumnProxy>
<ColumnProxy name="nombre" id="E0D6AFBB-7CFE-7028-511C-0216AE58684F">
<createdBy>usuario</createdBy>
<createdTime>2026-03-19 19:55:15 UTC</createdTime>
<ownerDesignName>DMD</ownerDesignName>
</ColumnProxy>
<ColumnProxy name="tlf_contacto" id="FCDFE54C-70A1-994E-B747-F2014BC7E335">
<createdBy>usuario</createdBy>
<createdTime>2026-03-19 19:55:15 UTC</createdTime>
<ownerDesignName>DMD</ownerDesignName>
</ColumnProxy>
<ColumnProxy name="id_usuario" id="FFCCC1DC-25F1-AAF9-929A-F8CE1EE30F70">
<createdBy>usuario</createdBy>
<createdTime>2026-03-19 19:55:15 UTC</createdTime>
<ownerDesignName>DMD</ownerDesignName>
</ColumnProxy>
</columnProxies>
<foreignKeys>
<ForeignKey class="oracle.dbtools.crest.model.design.storage.oracle.v10g.FKProxyOraclev10g" name="usuario_centro_fk" id="3104D056-BCB8-91B3-FFF6-3A9B77A2D857">
<createdBy>usuario</createdBy>
<createdTime>2026-03-19 19:55:15 UTC</createdTime>
<ownerDesignName>DMD</ownerDesignName>
</ForeignKey>
</foreignKeys>
<primaryKeys>
<PrimaryKey class="oracle.dbtools.crest.model.design.storage.oracle.v10g.PKProxyOraclev10g" name="usuario_pk" id="50AF8429-FBFD-F7B3-EFF5-06BAA2ABA74E">
<createdBy>usuario</createdBy>
<createdTime>2026-03-19 19:55:15 UTC</createdTime>
<ownerDesignName>DMD</ownerDesignName>
<indexSort>SORTED</indexSort>
</PrimaryKey>
</primaryKeys>
<uniqueKeys>
<UniqueKey class="oracle.dbtools.crest.model.design.storage.oracle.v10g.UniqueOraclev10g" name="usuario__un" id="1D47467B-3B75-E52C-DC9C-75E81B4317CD">
<createdBy>usuario</createdBy>
<createdTime>2026-03-19 19:55:15 UTC</createdTime>
<ownerDesignName>DMD</ownerDesignName>
<indexSort>SORTED</indexSort>
</UniqueKey>
</uniqueKeys>
</TableProxyOraclev20c>